app/__init__.py
app/app_config.py
app/gpio.py
app/routes.py
app/trial_state_machine.py
skinnerbox_source-0.4.14.dist-info/METADATA
skinnerbox_source-0.4.14.dist-info/WHEEL
skinnerbox_source-0.4.14.dist-info/top_level.txt
skinnerbox_source-0.4.14.dist-info/RECORD
